{
    "1": [
        {
            "hub": "2",
            "weight": 1
        },
        {
            "hub": "4",
            "weight": 4
        }
    ],
    "2": [
        {
            "hub": "1",
            "weight": 1
        },
        {
            "hub": "3",
            "weight": 10
        },
        {
            "hub": "5",
            "weight": 4
        }
    ],
    "3": [
        {
            "hub": "2",
            "weight": 10
        },
        {
            "hub": "4",
            "weight": 6
        },
        {
            "hub": "6",
            "weight": 5
        }
    ],
    "4": [
        {
            "hub": "1",
            "weight": 4
        },
        {
            "hub": "3",
            "weight": 6
        },
        {
            "hub": "7",
            "weight": 9
        },
        {
            "hub": "10",
            "weight": 2
        }
    ],
    "5": [
        {
            "hub": "2",
            "weight": 4
        },
        {
            "hub": "6",
            "weight": 7
        }
    ],
    "6": [
        {
            "hub": "3",
            "weight": 5
        },
        {
            "hub": "5",
            "weight": 7
        },
        {
            "hub": "7",
            "weight": 6
        },
        {
            "hub": "8",
            "weight": 3
        }
    ],
    "7": [
        {
            "hub": "4",
            "weight": 9
        },
        {
            "hub": "6",
            "weight": 6
        },
        {
            "hub": "9",
            "weight": 7
        },
        {
            "hub": "10",
            "weight": 1
        }
    ],
    "8": [
        {
            "hub": "6",
            "weight": 3
        },
        {
            "hub": "9",
            "weight": 2
        }
    ],
    "9": [
        {
            "hub": "7",
            "weight": 7
        },
        {
            "hub": "8",
            "weight": 2
        },
        {
            "hub": "10",
            "weight": 9
        }
    ],
    "10": [
        {
            "hub": "4",
            "weight": 2
        },
        {
            "hub": "7",
            "weight": 1
        },
        {
            "hub": "9",
            "weight": 9
        }
    ]
}
